fastcodedog/__init__.py
fastcodedog/cli.py
fastcodedog/common/__init__.py
fastcodedog/common/clean_expired.py
fastcodedog/common/source_file_path.py
fastcodedog/common/write_file.py
fastcodedog/context/__init__.py
fastcodedog/context/api/__init__.py
fastcodedog/context/api/api.py
fastcodedog/context/api/endpoint.py
fastcodedog/context/api/oauth2.py
fastcodedog/context/api/param.py
fastcodedog/context/common/__init__.py
fastcodedog/context/common/get_context_object.py
fastcodedog/context/common/get_relationship.py
fastcodedog/context/context.py
fastcodedog/context/contextbase.py
fastcodedog/context/crud/__init__.py
fastcodedog/context/crud/column.py
fastcodedog/context/crud/crud.py
fastcodedog/context/crud/default_value.py
fastcodedog/context/crud/join_relationship.py
fastcodedog/context/crud/query.py
fastcodedog/context/model/__init__.py
fastcodedog/context/model/additional_method.py
fastcodedog/context/model/case.py
fastcodedog/context/model/column.py
fastcodedog/context/model/computed_property.py
fastcodedog/context/model/copy_method.py
fastcodedog/context/model/model.py
fastcodedog/context/model/parameter.py
fastcodedog/context/model/relationship.py
fastcodedog/context/schema/__init__.py
fastcodedog/context/schema/alias_generator.py
fastcodedog/context/schema/field.py
fastcodedog/context/schema/response_schema.py
fastcodedog/context/schema/schema.py
fastcodedog/context/schema/sub_object.py
fastcodedog/context/setting/__init__.py
fastcodedog/context/setting/config.py
fastcodedog/context/setting/extend_app.py
fastcodedog/context/setting/listen.py
fastcodedog/context/setting/project.py
fastcodedog/context/setting/source_directory.py
fastcodedog/context/setting/tenant.py
fastcodedog/generation/__init__.py
fastcodedog/generation/api/__init__.py
fastcodedog/generation/api/api.py
fastcodedog/generation/api/api_function.py
fastcodedog/generation/api/config.py
fastcodedog/generation/api/db.py
fastcodedog/generation/api/generation.py
fastcodedog/generation/api/main.py
fastcodedog-3.2.3.dist-info/entry_points.txt
fastcodedog-3.2.3.dist-info/METADATA
fastcodedog-3.2.3.dist-info/WHEEL
fastcodedog-3.2.3.dist-info/RECORD
