Metadata-Version: 2.1
Name: fastcodedog
Version: 3.2.3
Summary: 
License: MIT
Author: taohoo
Author-email: taohoo@163.com
Requires-Python: >=3.10
Classifier: License :: OSI Approved :: MIT License
Classifier: Programming Language :: Python :: 3
Classifier: Programming Language :: Python :: 3.10
Classifier: Programming Language :: Python :: 3.11
Classifier: Programming Language :: Python :: 3.12
Requires-Dist: autopep8 (>=2.2.0)
Requires-Dist: inflect (>=7.2.1)
Requires-Dist: json5 (>=0.9.25)
